amnparse/__init__.py
amnparse/args.py
amnparse/ini.py
amnparse-0.1.dist-info/LICENSE
amnparse-0.1.dist-info/METADATA
amnparse-0.1.dist-info/WHEEL
amnparse-0.1.dist-info/top_level.txt
amnparse-0.1.dist-info/RECORD
